nr/__init__.py
nr/databind/__init__.py
nr/databind/core/__init__.py
nr/databind/core/collection.py
nr/databind/core/datatypes.py
nr/databind/core/decorations.py
nr/databind/core/struct.py
nr/databind/core/union.py
nr.databind.core-0.0.22.dist-info/LICENSE.txt
nr.databind.core-0.0.22.dist-info/METADATA
nr.databind.core-0.0.22.dist-info/WHEEL
nr.databind.core-0.0.22.dist-info/entry_points.txt
nr.databind.core-0.0.22.dist-info/top_level.txt
nr.databind.core-0.0.22.dist-info/zip-safe
nr.databind.core-0.0.22.dist-info/RECORD
