Metadata-Version: 2.1
Name: nr.databind.core
Version: 0.0.22
Summary: Bind structured data directly to typed objects.
Home-page: https://git.niklasrosenstein.com/NiklasRosenstein/nr
Author: Niklas Rosenstein
Author-email: rosensteinniklas@gmail.com
License: MIT
Platform: UNKNOWN
Requires-Dist: nr.collections (<1.0.0,>=0.0.1)
Requires-Dist: nr.interface (<0.1.0,>=0.0.1)
Requires-Dist: nr.stream (<0.1.0,>=0.0.1)
Requires-Dist: nr.pylang.utils (<0.1.0,>=0.0.3)
